keydb/__init__.py
keydb/client.py
tests/__init__.py
tests/cmd.py
keydb-0.0.1.dist-info/LICENSE
keydb-0.0.1.dist-info/METADATA
keydb-0.0.1.dist-info/WHEEL
keydb-0.0.1.dist-info/top_level.txt
keydb-0.0.1.dist-info/RECORD
